rwilinski/aws-lambda-golang/__init__.py
rwilinski/aws-lambda-golang/py.typed
rwilinski/aws-lambda-golang/_jsii/__init__.py
rwilinski/aws-lambda-golang/_jsii/aws-lambda-golang@0.1.1.jsii.tgz
rwilinski.aws_lambda_golang-0.1.1.dist-info/METADATA
rwilinski.aws_lambda_golang-0.1.1.dist-info/WHEEL
rwilinski.aws_lambda_golang-0.1.1.dist-info/top_level.txt
rwilinski.aws_lambda_golang-0.1.1.dist-info/RECORD
