Metadata-Version: 2.1
Name: rwilinski.aws-lambda-golang
Version: 0.1.1
Summary: CDK Construct for AWS Lambda in Golang
Home-page: https://github.com/RafalWilinski/aws-lambda-golang-cdk
Author: Rafal Wilinski<raf.wilinski@gmail.com>
License: Apache-2.0
Project-URL: Source, https://github.com/RafalWilinski/aws-lambda-golang-cdk.git
Platform: UNKNOWN
Classifier: Intended Audience :: Developers
Classifier: Operating System :: OS Independent
Classifier: Programming Language :: JavaScript
Classifier: Programming Language :: Python :: 3 :: Only
Classifier: Programming Language :: Python :: 3.6
Classifier: Programming Language :: Python :: 3.7
Classifier: Programming Language :: Python :: 3.8
Classifier: Typing :: Typed
Classifier: Development Status :: 4 - Beta
Classifier: License :: OSI Approved
Requires-Python: >=3.6
Requires-Dist: jsii (<2.0.0,>=1.6.0)
Requires-Dist: publication (>=0.0.3)
Requires-Dist: aws-cdk.aws-lambda (<2.0.0,>=1.43.0)
Requires-Dist: aws-cdk.core (<2.0.0,>=1.43.0)
Requires-Dist: constructs (<4.0.0,>=3.0.3)
